yaml_reference/__init__.py
yaml_reference/anchor.py
yaml_reference/cli.py
yaml_reference/errors.py
yaml_reference/reference.py
yaml_reference/yaml.py
yaml_reference-0.3.4.dist-info/LICENSE
yaml_reference-0.3.4.dist-info/METADATA
yaml_reference-0.3.4.dist-info/WHEEL
yaml_reference-0.3.4.dist-info/entry_points.txt
yaml_reference-0.3.4.dist-info/RECORD
