Metadata-Version: 2.3
Name: yaml-reference
Version: 0.3.4
Summary: Extension package built on top of  `ruamel.yaml` to support cross-file references in YAML files using tags `!reference` and `!reference-all`.
License: MIT
Keywords: yaml,yml,reference,yaml-reference,ruamel,ruamel-yaml,jmespath
Author: David Sillman
Author-email: dsillman2000@gmail.com
Requires-Python: >=3.9,<4.0
Classifier: Development Status :: 4 - Beta
Classifier: Intended Audience :: Developers
Classifier: Topic :: Software Development :: Libraries :: Python Modules
Classifier: Topic :: File Formats
Classifier: Topic :: Utilities
Classifier: Programming Language :: Python :: 3.9
Classifier: Programming Language :: Python :: 3.10
Classifier: Programming Language :: Python :: 3.11
Classifier: Programming Language :: Python :: 3.12
Classifier: Programming Language :: Python :: 3.13
Requires-Dist: jmespath (>=1.0.1,<2.0.0)
Requires-Dist: ruamel-yaml (>=0.18.11,<0.19.0)
Project-URL: Repository, https://github.com/dsillman2000/yaml-reference.git
